BMI_Calculator_Hoyong/BMI_Calculation.py
BMI_Calculator_Hoyong-0.0.0.1.dist-info/METADATA
BMI_Calculator_Hoyong-0.0.0.1.dist-info/WHEEL
BMI_Calculator_Hoyong-0.0.0.1.dist-info/top_level.txt
BMI_Calculator_Hoyong-0.0.0.1.dist-info/RECORD
